{
  "db_name": "PostgreSQL",
  "query": "select decision_id, message_id from evidence\n             where decision_id = any($1)\n             order by message_id",
  "describe": {
    "columns": [
      {
        "ordinal": 0,
        "name": "decision_id",
        "type_info": "Uuid"
      },
      {
        "ordinal": 1,
        "name": "message_id",
        "type_info": "Uuid"
      }
    ],
    "parameters": {
      "Left": [
        "UuidArray"
      ]
    },
    "nullable": [
      false,
      false
    ]
  },
  "hash": "9126bad6e6ee9d70ad1b4415f39ab1a3e6af36e750086ee50e204cff49576690"
}
